agent_registry_router/__init__.py
agent_registry_router/py.typed
agent_registry_router/adapters/__init__.py
agent_registry_router/adapters/pydantic_ai/README.md
agent_registry_router/adapters/pydantic_ai/__init__.py
agent_registry_router/adapters/pydantic_ai/dispatcher.py
agent_registry_router/core/__init__.py
agent_registry_router/core/events.py
agent_registry_router/core/exceptions.py
agent_registry_router/core/prompting.py
agent_registry_router/core/registry.py
agent_registry_router/core/routing.py
agent_registry_router-0.2.5.dist-info/METADATA
agent_registry_router-0.2.5.dist-info/WHEEL
agent_registry_router-0.2.5.dist-info/licenses/LICENSE
agent_registry_router-0.2.5.dist-info/RECORD
