Metadata-Version: 2.4
Name: agent-registry-router
Version: 0.2.5
Summary: Registry-driven LLM routing: build classifier prompts from agent descriptions, validate decisions, and dispatch.
Project-URL: Homepage, https://github.com/agibson22/agent-registry-router
Project-URL: Repository, https://github.com/agibson22/agent-registry-router
Project-URL: Issues, https://github.com/agibson22/agent-registry-router/issues
Author-email: ag <agibson22@gmail.com>
License:                                  Apache License
License-File: LICENSE
Classifier: License :: OSI Approved :: Apache Software License
Classifier: Programming Language :: Python :: 3
Classifier: Programming Language :: Python :: 3 :: Only
Classifier: Programming Language :: Python :: 3.10
Classifier: Programming Language :: Python :: 3.11
Classifier: Programming Language :: Python :: 3.12
Classifier: Programming Language :: Python :: 3.13
Classifier: Typing :: Typed
Requires-Python: >=3.10
Requires-Dist: pydantic>=2.0.0
Provides-Extra: dev
Requires-Dist: black>=24.8.0; extra == 'dev'
Requires-Dist: mypy>=1.11.0; extra == 'dev'
Requires-Dist: pytest-cov>=4.1.0; extra == 'dev'
Requires-Dist: pytest>=8.0.0; extra == 'dev'
Requires-Dist: ruff>=0.7.0; extra == 'dev'
Provides-Extra: pydanticai
Requires-Dist: pydantic-ai; extra == 'pydanticai'
